{
  "type": "Feature",
  "properties": {
    "gn:admin1_code":"35.0",
    "gn:asciiname":"Sugar Loaf",
    "gn:country_code":"BS",
    "gn:dem":-9999,
    "gn:feature_class":"P",
    "gn:feature_code":"PPL",
    "gn:name":"Sugar Loaf",
    "gn:population":0,
    "gn:timezone":"America/Nassau",
    "iso:country":"BS",
    "wof:name":"Sugar Loaf",
    "wof:placetype":"locality"
},
  "geometry": {"coordinates":[-74.51666999999998,23.65],"type":"Point"}
}