{
  "type": "Feature",
  "properties": {
    "gn:admin1_code":"47.0",
    "gn:asciiname":"Lowe Sound Settlement",
    "gn:country_code":"BS",
    "gn:dem":4,
    "gn:feature_class":"P",
    "gn:feature_code":"PPL",
    "gn:name":"Lowe Sound Settlement",
    "gn:population":0,
    "gn:timezone":"America/Nassau",
    "iso:country":"BS",
    "name:eng_x_preferred":[
        "Lowe Sound Settlement"
    ],
    "name:eng_x_variant":[
        "Lowe Sound"
    ],
    "wof:name":"Lowe Sound Settlement",
    "wof:placetype":"locality"
},
  "geometry": {"coordinates":[-78.0917,25.14891],"type":"Point"}
}