{
  "type": "Feature",
  "properties": {
    "iso:country":"BS",
    "name:deu_x_preferred":[
        "Fresh Creek"
    ],
    "name:eng_x_preferred":[
        "Fresh Creek"
    ],
    "qs:gn_pop":0,
    "qs:name":"Fresh Creek",
    "qs:name_adm0":"The Bahamas",
    "qs:name_adm1":"Central Andros",
    "qs:photos":484,
    "qs:photos_1k":98,
    "qs:photos_9k":2,
    "qs:photos_9r":5,
    "qs:photos_all":484,
    "qs:photos_sr":7,
    "qs:placetype":"Town",
    "qs:pop_sr":"0",
    "qs:woe_adm0":23424758,
    "wd:wordcount":80,
    "wof:name":"Fresh Creek",
    "wof:placetype":"locality"
},
  "geometry": {"coordinates":[-77.760887,24.689525],"type":"Point"}
}