{
  "type": "Feature",
  "properties": {
    "iso:country":"BS",
    "qs:gn_pop":0,
    "qs:name":"Hard Bargain",
    "qs:name_adm0":"The Bahamas",
    "qs:name_adm1":"Moore's Island",
    "qs:photos":74,
    "qs:photos_1k":15,
    "qs:photos_9k":1,
    "qs:photos_9r":2,
    "qs:photos_all":74,
    "qs:photos_sr":2,
    "qs:placetype":"Town",
    "qs:pop_sr":"0",
    "qs:woe_adm0":23424758,
    "wd:wordcount":34,
    "wof:name":"Hard Bargain",
    "wof:placetype":"locality"
},
  "geometry": {"coordinates":[-77.569828,26.304582],"type":"Point"}
}