{
  "type": "Feature",
  "properties": {
    "gn:admin1_code":"54.0",
    "gn:asciiname":"Hope Estate",
    "gn:country_code":"BS",
    "gn:dem":-9999,
    "gn:feature_class":"P",
    "gn:feature_code":"PPL",
    "gn:name":"Hope Estate",
    "gn:population":0,
    "gn:timezone":"America/Nassau",
    "iso:country":"BS",
    "wof:name":"Hope Estate",
    "wof:placetype":"locality"
},
  "geometry": {"coordinates":[-78.93333,26.66667],"type":"Point"}
}