{
  "type": "Feature",
  "properties": {
    "gn:admin1_code":"23.0",
    "gn:asciiname":"Clifton",
    "gn:country_code":"BS",
    "gn:dem":-9999,
    "gn:feature_class":"P",
    "gn:feature_code":"PPL",
    "gn:name":"Clifton",
    "gn:population":0,
    "gn:timezone":"America/Nassau",
    "iso:country":"BS",
    "wof:name":"Clifton",
    "wof:placetype":"locality"
},
  "geometry": {"coordinates":[-77.56667,25.01667],"type":"Point"}
}