{
  "type": "Feature",
  "properties": {
    "gn:admin1_code":"10.0",
    "gn:asciiname":"Rolleville",
    "gn:country_code":"BS",
    "gn:dem":18,
    "gn:feature_class":"P",
    "gn:feature_code":"PPL",
    "gn:name":"Rolleville",
    "gn:population":0,
    "gn:timezone":"America/Nassau",
    "iso:country":"BS",
    "name:und_x_variant":[
        "Rollesville",
        "Roseville",
        "Rolleville"
    ],
    "wof:name":"Rolleville",
    "wof:placetype":"locality"
},
  "geometry": {"coordinates":[-75.98484000000001,23.67332],"type":"Point"}
}