{
  "type": "Feature",
  "properties": {
    "gn:admin1_code":"10.0",
    "gn:asciiname":"Rolleville",
    "gn:country_code":"BS",
    "gn:dem":18,
    "gn:feature_class":"P",
    "gn:feature_code":"PPL",
    "gn:name":"Rolleville",
    "gn:population":0,
    "gn:timezone":"America/Nassau",
    "iso:country":"BS",
    "name:cat_x_preferred":[
        "Rolleville"
    ],
    "name:ceb_x_preferred":[
        "Rolleville"
    ],
    "name:deu_x_preferred":[
        "Rolleville"
    ],
    "name:epo_x_preferred":[
        "Rolleville"
    ],
    "name:eus_x_preferred":[
        "Rolleville"
    ],
    "name:fra_x_preferred":[
        "Rolleville"
    ],
    "name:hun_x_preferred":[
        "Rolleville"
    ],
    "name:ita_x_preferred":[
        "Rolleville"
    ],
    "name:kaz_x_preferred":[
        "\u0420\u043e\u043b\u044c\u0432\u0438\u043b\u044c"
    ],
    "name:lat_x_preferred":[
        "Rolleville"
    ],
    "name:mlg_x_preferred":[
        "Rolleville"
    ],
    "name:msa_x_preferred":[
        "Rolleville"
    ],
    "name:nld_x_preferred":[
        "Rolleville"
    ],
    "name:oci_x_preferred":[
        "Rolleville"
    ],
    "name:pms_x_preferred":[
        "Rolleville"
    ],
    "name:pol_x_preferred":[
        "Rolleville"
    ],
    "name:por_x_preferred":[
        "Rolleville"
    ],
    "name:ron_x_preferred":[
        "Rolleville"
    ],
    "name:slk_x_preferred":[
        "Rolleville"
    ],
    "name:spa_x_preferred":[
        "Rolleville"
    ],
    "name:swe_x_preferred":[
        "Rolleville"
    ],
    "name:ukr_x_preferred":[
        "\u0420\u043e\u043b\u044c\u0432\u0456\u043b\u044c"
    ],
    "name:und_x_variant":[
        "Rollesville",
        "Roseville"
    ],
    "name:vie_x_preferred":[
        "Rolleville"
    ],
    "name:vol_x_preferred":[
        "Rolleville"
    ],
    "name:war_x_preferred":[
        "Rolleville"
    ],
    "wof:name":"Rolleville",
    "wof:placetype":"locality"
},
  "geometry": {"coordinates":[-75.98484000000001,23.67332],"type":"Point"}
}