{
  "type": "Feature",
  "properties": {
    "gn:admin1_code":"15.0",
    "gn:asciiname":"Adderly",
    "gn:cc2":"BS",
    "gn:country_code":"BS",
    "gn:dem":31,
    "gn:feature_class":"P",
    "gn:feature_code":"PPL",
    "gn:name":"Adderly",
    "gn:population":0,
    "gn:timezone":"America/Nassau",
    "iso:country":"BS",
    "name:ita_x_preferred":[
        "Adderly"
    ],
    "name:und_x_variant":[
        "Adderleys"
    ],
    "wof:name":"Adderly",
    "wof:placetype":"locality"
},
  "geometry": {"coordinates":[-75.2542,23.58059],"type":"Point"}
}