{
  "type": "Feature",
  "properties": {
    "gn:country":"BS",
    "gn:fcode":"PPLA",
    "gn:pop":240,
    "iso:country":"BS",
    "name:ceb_x_preferred":[
        "Colonel Hill"
    ],
    "name:eng_x_preferred":[
        "Colonel Hill"
    ],
    "name:fas_x_preferred":[
        "\u06a9\u0644\u0646\u0644 \u0647\u06cc\u0644"
    ],
    "name:fra_x_preferred":[
        "Colonel Hill"
    ],
    "name:jpn_x_preferred":[
        "\u30b3\u30ed\u30cd\u30eb\u30fb\u30d2\u30eb"
    ],
    "name:nld_x_preferred":[
        "Colonel Hill"
    ],
    "name:pol_x_preferred":[
        "Colonel Hill"
    ],
    "name:ron_x_preferred":[
        "Colonel Hill"
    ],
    "name:rus_x_preferred":[
        "\u041a\u043e\u043d\u0435\u043b-\u0425\u0438\u043b\u043b"
    ],
    "name:swe_x_preferred":[
        "Colonel Hill"
    ],
    "name:urd_x_preferred":[
        "\u06a9\u0631\u0646\u0644 \u06c1\u0644"
    ],
    "qs:name":"Colonel Hill",
    "qs:photos_9r":0,
    "qs:photos_sr":0,
    "qs:pop_sr":"2",
    "wd:wordcount":47,
    "wof:name":"Colonel Hill",
    "wof:placetype":"locality",
    "wof:population":240
},
  "geometry": {"coordinates":[-74.21666999999999,22.76667],"type":"Point"}
}