{
  "type": "Feature",
  "properties": {
    "gn:admin1_code":"15.0",
    "gn:asciiname":"McKanns",
    "gn:cc2":"BS",
    "gn:country_code":"BS",
    "gn:dem":-9999,
    "gn:feature_class":"P",
    "gn:feature_code":"PPL",
    "gn:name":"McKanns",
    "gn:population":0,
    "gn:timezone":"America/Nassau",
    "iso:country":"BS",
    "name:und_x_variant":[
        "McCanns",
        "McKanns"
    ],
    "wof:name":"McKanns",
    "wof:placetype":"locality"
},
  "geometry": {"coordinates":[-75.16667,23.36667000000001],"type":"Point"}
}