{
  "type": "Feature",
  "properties": {
    "gn:admin1_code":"35.0",
    "gn:asciiname":"Long Bay",
    "gn:country_code":"BS",
    "gn:dem":7,
    "gn:feature_class":"P",
    "gn:feature_code":"PPL",
    "gn:name":"Long Bay",
    "gn:population":0,
    "gn:timezone":"America/Nassau",
    "iso:country":"BS",
    "name:ceb_x_preferred":[
        "Long Bay"
    ],
    "name:deu_x_preferred":[
        "Long Bay"
    ],
    "name:swe_x_preferred":[
        "Long Bay"
    ],
    "wof:name":"Long Bay",
    "wof:placetype":"locality"
},
  "geometry": {"coordinates":[-74.52542,24.01151],"type":"Point"}
}