{
  "type": "Feature",
  "properties": {
    "gn:admin1_code":"15.0",
    "gn:asciiname":"Mortimers",
    "gn:country_code":"BS",
    "gn:dem":5,
    "gn:feature_class":"P",
    "gn:feature_code":"PPL",
    "gn:name":"Mortimers",
    "gn:population":0,
    "gn:timezone":"America/Nassau",
    "iso:country":"BS",
    "name:und_x_variant":[
        "Mortimers Settlement",
        "Mortimers"
    ],
    "wof:name":"Mortimers",
    "wof:placetype":"locality"
},
  "geometry": {"coordinates":[-74.87432,22.90621],"type":"Point"}
}