{
  "type": "Feature",
  "properties": {
    "gn:admin1_code":"10.0",
    "gn:asciiname":"Forest",
    "gn:country_code":"BS",
    "gn:dem":7,
    "gn:feature_class":"P",
    "gn:feature_code":"PPL",
    "gn:name":"Forest",
    "gn:population":0,
    "gn:timezone":"America/Nassau",
    "iso:country":"BS",
    "name:und_x_variant":[
        "The Forest",
        "Forest Settlement",
        "Forest"
    ],
    "wof:name":"Forest",
    "wof:placetype":"locality"
},
  "geometry": {"coordinates":[-75.91443000000002,23.58697],"type":"Point"}
}