{
  "type": "Feature",
  "properties": {
    "gn:admin1_code":"15.0",
    "gn:asciiname":"Anderson",
    "gn:country_code":"BS",
    "gn:dem":5,
    "gn:feature_class":"P",
    "gn:feature_code":"PPL",
    "gn:name":"Anderson",
    "gn:population":0,
    "gn:timezone":"America/Nassau",
    "iso:country":"BS",
    "name:ara_x_preferred":[
        "\u0623\u0646\u062f\u0631\u0633\u0648\u0646"
    ],
    "name:aze_x_preferred":[
        "Anderson"
    ],
    "name:bel_x_preferred":[
        "\u0410\u043d\u0434\u044d\u0440\u0441\u0430\u043d"
    ],
    "name:bul_x_preferred":[
        "\u0410\u043d\u0434\u0435\u0440\u0441\u044a\u043d"
    ],
    "name:cat_x_preferred":[
        "Anderson"
    ],
    "name:ceb_x_preferred":[
        "Anderson"
    ],
    "name:ces_x_preferred":[
        "Anderson"
    ],
    "name:dan_x_preferred":[
        "Anderson"
    ],
    "name:deu_x_preferred":[
        "Anderson"
    ],
    "name:est_x_preferred":[
        "Anderson"
    ],
    "name:fas_x_preferred":[
        "\u0627\u0646\u062f\u0631\u0633\u0648\u0646"
    ],
    "name:fin_x_preferred":[
        "Anderson"
    ],
    "name:fra_x_preferred":[
        "Anderson"
    ],
    "name:heb_x_preferred":[
        "\u05d0\u05e0\u05d3\u05e8\u05e1\u05d5\u05df"
    ],
    "name:hrv_x_preferred":[
        "Anderson"
    ],
    "name:hun_x_preferred":[
        "Anderson"
    ],
    "name:ita_x_preferred":[
        "Anderson"
    ],
    "name:jpn_x_preferred":[
        "\u30a2\u30f3\u30c0\u30fc\u30bd\u30f3"
    ],
    "name:kor_x_preferred":[
        "\uc564\ub354\uc2a8"
    ],
    "name:lit_x_preferred":[
        "Anderson"
    ],
    "name:nld_x_preferred":[
        "Anderson"
    ],
    "name:pol_x_preferred":[
        "Anderson"
    ],
    "name:por_x_preferred":[
        "Anderson"
    ],
    "name:slv_x_preferred":[
        "Anderson"
    ],
    "name:spa_x_preferred":[
        "Anderson"
    ],
    "name:srp_x_preferred":[
        "\u0410\u043d\u0434\u0435\u0440\u0441\u043e\u043d"
    ],
    "name:swe_x_preferred":[
        "Anderson"
    ],
    "name:tur_x_preferred":[
        "Anderson"
    ],
    "name:ukr_x_preferred":[
        "\u0410\u043d\u0434\u0435\u0440\u0441\u043e\u043d"
    ],
    "name:urd_x_preferred":[
        "\u0627\u06cc\u0646\u0688\u0631\u0633\u0646"
    ],
    "name:vie_x_preferred":[
        "Anderson"
    ],
    "name:vol_x_preferred":[
        "Anderson"
    ],
    "name:zho_x_preferred":[
        "\u5b89\u5fb7\u68ee"
    ],
    "wof:name":"Anderson",
    "wof:placetype":"locality"
},
  "geometry": {"coordinates":[-75.23333000000002,23.53333],"type":"Point"}
}