{
  "type": "Feature",
  "properties": {
    "gn:admin1_code":"15.0",
    "gn:asciiname":"Anderson",
    "gn:country_code":"BS",
    "gn:dem":5,
    "gn:feature_class":"P",
    "gn:feature_code":"PPL",
    "gn:name":"Anderson",
    "gn:population":0,
    "gn:timezone":"America/Nassau",
    "iso:country":"BS",
    "wof:name":"Anderson",
    "wof:placetype":"locality"
},
  "geometry": {"coordinates":[-75.23333000000002,23.53333],"type":"Point"}
}