{
  "type": "Feature",
  "properties": {
    "gn:admin1_code":"10.0",
    "gn:asciiname":"Curtis",
    "gn:country_code":"BS",
    "gn:dem":8,
    "gn:feature_class":"P",
    "gn:feature_code":"PPL",
    "gn:name":"Curtis",
    "gn:population":0,
    "gn:timezone":"America/Nassau",
    "iso:country":"BS",
    "wof:name":"Curtis",
    "wof:placetype":"locality"
},
  "geometry": {"coordinates":[-75.96666999999999,23.63333],"type":"Point"}
}