{
  "type": "Feature",
  "properties": {
    "gn:admin1_code":"47.0",
    "gn:asciiname":"August Town",
    "gn:country_code":"BS",
    "gn:dem":9,
    "gn:feature_class":"P",
    "gn:feature_code":"PPL",
    "gn:name":"August Town",
    "gn:population":0,
    "gn:timezone":"America/Nassau",
    "iso:country":"BS",
    "wof:name":"August Town",
    "wof:placetype":"locality"
},
  "geometry": {"coordinates":[-77.98333000000002,25.03333],"type":"Point"}
}