{
  "type": "Feature",
  "properties": {
    "gn:admin1_code":"15.0",
    "gn:asciiname":"Cabbage Point",
    "gn:country_code":"BS",
    "gn:dem":4,
    "gn:feature_class":"P",
    "gn:feature_code":"PPL",
    "gn:name":"Cabbage Point",
    "gn:population":0,
    "gn:timezone":"America/Nassau",
    "iso:country":"BS",
    "name:und_x_variant":[
        "Cabbage Point Settlement",
        "Cabbage Point"
    ],
    "wof:name":"Cabbage Point",
    "wof:placetype":"locality"
},
  "geometry": {"coordinates":[-74.88568000000002,22.93279],"type":"Point"}
}