{
  "type": "Feature",
  "properties": {
    "gn:admin1_code":"23.0",
    "gn:asciiname":"Coral Harbour",
    "gn:country_code":"BS",
    "gn:dem":11,
    "gn:feature_class":"P",
    "gn:feature_code":"PPL",
    "gn:name":"Coral Harbour",
    "gn:population":0,
    "gn:timezone":"America/Nassau",
    "iso:country":"BS",
    "name:und_x_variant":[
        "Coral Harbor",
        "Coral Harbour"
    ],
    "wof:name":"Coral Harbour",
    "wof:placetype":"locality"
},
  "geometry": {"coordinates":[-77.46534,24.98176],"type":"Point"}
}