{
  "type": "Feature",
  "properties": {
    "gn:admin1_code":"23.0",
    "gn:asciiname":"Coral Harbour",
    "gn:country_code":"BS",
    "gn:dem":11,
    "gn:feature_class":"P",
    "gn:feature_code":"PPL",
    "gn:name":"Coral Harbour",
    "gn:population":0,
    "gn:timezone":"America/Nassau",
    "iso:country":"BS",
    "name:bel_x_preferred":[
        "\u041a\u043e\u0440\u0430\u043b-\u0425\u0430\u0440\u0431\u0430\u0440"
    ],
    "name:cat_x_preferred":[
        "Coral Harbour"
    ],
    "name:ceb_x_preferred":[
        "Coral Harbour"
    ],
    "name:deu_x_preferred":[
        "Coral Harbour"
    ],
    "name:fas_x_preferred":[
        "\u06a9\u0648\u0631\u0627\u0644 \u0647\u0627\u0631\u0628\u0648\u0631"
    ],
    "name:fin_x_preferred":[
        "Coral Harbour"
    ],
    "name:fra_x_preferred":[
        "Coral Harbour"
    ],
    "name:iku_x_preferred":[
        "\u14f4\u14ea\u14d6\u1466"
    ],
    "name:ita_x_preferred":[
        "Coral Harbour"
    ],
    "name:kal_x_preferred":[
        "Coral Harbour"
    ],
    "name:ltz_x_preferred":[
        "Coral Harbour"
    ],
    "name:pol_x_preferred":[
        "Coral Harbour"
    ],
    "name:por_x_preferred":[
        "Coral Harbour"
    ],
    "name:rus_x_preferred":[
        "\u041a\u043e\u0440\u0430\u043b-\u0425\u0430\u0440\u0431\u043e\u0440"
    ],
    "name:sqi_x_preferred":[
        "Coral Harbour"
    ],
    "name:swe_x_preferred":[
        "Coral Harbour"
    ],
    "name:ukr_x_preferred":[
        "\u041a\u043e\u0440\u0430\u043b-\u0413\u0430\u0440\u0431\u043e\u0440"
    ],
    "name:und_x_variant":[
        "Coral Harbor"
    ],
    "wof:name":"Coral Harbour",
    "wof:placetype":"locality"
},
  "geometry": {"coordinates":[-77.46534,24.98176],"type":"Point"}
}