{
  "type": "Feature",
  "properties": {
    "gn:admin1_code":"6.0",
    "gn:asciiname":"Bennett's Harbour",
    "gn:country_code":"BS",
    "gn:dem":9,
    "gn:feature_class":"P",
    "gn:feature_code":"PPL",
    "gn:name":"Bennett\u2019s Harbour",
    "gn:population":0,
    "gn:timezone":"America/Nassau",
    "iso:country":"BS",
    "name:und_x_variant":[
        "Bennett\u2019s Harbour Settlement",
        "Bennets Harbour",
        "Bennetts Harbor",
        "Bennet Harbour",
        "Bennett\u2019s Harbour"
    ],
    "wof:name":"Bennett's Harbour",
    "wof:placetype":"locality"
},
  "geometry": {"coordinates":[-75.63989000000002,24.56347],"type":"Point"}
}