{
  "type": "Feature",
  "properties": {
    "gn:admin1_code":"35.0",
    "gn:asciiname":"Trial Farm",
    "gn:country_code":"BS",
    "gn:dem":4,
    "gn:feature_class":"P",
    "gn:feature_code":"PPL",
    "gn:name":"Trial Farm",
    "gn:population":0,
    "gn:timezone":"America/Nassau",
    "iso:country":"BS",
    "name:deu_x_preferred":[
        "Trial Farm"
    ],
    "name:fra_x_preferred":[
        "Trial Farm"
    ],
    "name:ita_x_preferred":[
        "Trial Farm"
    ],
    "name:nds_x_preferred":[
        "Trial Farm"
    ],
    "name:pol_x_preferred":[
        "Trial Farm"
    ],
    "name:por_x_preferred":[
        "Trial Farm"
    ],
    "name:spa_x_preferred":[
        "Trial Farm"
    ],
    "wof:name":"Trial Farm",
    "wof:placetype":"locality"
},
  "geometry": {"coordinates":[-74.48333000000002,23.96667],"type":"Point"}
}