{
  "type": "Feature",
  "properties": {
    "gn:country":"BS",
    "gn:fcode":"PPL",
    "gn:pop":46525,
    "iso:country":"BS",
    "name:dut_x_preferred":[
        "Lucaya"
    ],
    "name:eng_x_preferred":[
        "Lucaya"
    ],
    "name:jpn_x_preferred":[
        "\u30eb\u30ab\u30e4"
    ],
    "name:swe_x_preferred":[
        "Lucaya"
    ],
    "name:tur_x_preferred":[
        "Lucaya"
    ],
    "qs:name":"Lucaya",
    "qs:photos_9r":0,
    "qs:photos_sr":0,
    "qs:pop_sr":"7",
    "wd:wordcount":149,
    "wof:name":"Lucaya",
    "wof:placetype":"locality",
    "wof:population":46525
},
  "geometry": {"coordinates":[-78.66667,26.53333],"type":"Point"}
}