{
  "type": "Feature",
  "properties": {
    "gn:admin1_code":"24.0",
    "gn:asciiname":"Abercorn",
    "gn:country_code":"BS",
    "gn:dem":-9999,
    "gn:feature_class":"P",
    "gn:feature_code":"PPL",
    "gn:name":"Abercorn",
    "gn:population":0,
    "gn:timezone":"America/Nassau",
    "iso:country":"BS",
    "wof:name":"Abercorn",
    "wof:placetype":"locality"
},
  "geometry": {"coordinates":[-73.95,22.36667000000001],"type":"Point"}
}