{
  "type": "Feature",
  "properties": {
    "gn:admin1_code":"24.0",
    "gn:asciiname":"Abercorn",
    "gn:country_code":"BS",
    "gn:dem":-9999,
    "gn:feature_class":"P",
    "gn:feature_code":"PPL",
    "gn:name":"Abercorn",
    "gn:population":0,
    "gn:timezone":"America/Nassau",
    "iso:country":"BS",
    "name:ang_x_preferred":[
        "Abercurnig"
    ],
    "name:deu_x_preferred":[
        "Abercorn"
    ],
    "name:eus_x_preferred":[
        "Abercorn"
    ],
    "name:fra_x_preferred":[
        "Abercorn"
    ],
    "name:gla_x_preferred":[
        "Obar Ch\u00f9irnidh"
    ],
    "name:gle_x_preferred":[
        "Obar Ch\u00fairnidh"
    ],
    "name:ita_x_preferred":[
        "Abercorn"
    ],
    "name:nld_x_preferred":[
        "Abercorn"
    ],
    "name:nno_x_preferred":[
        "Abercorn"
    ],
    "name:nor_x_preferred":[
        "Abercorn"
    ],
    "name:spa_x_preferred":[
        "Abercorn"
    ],
    "wof:name":"Abercorn",
    "wof:placetype":"locality"
},
  "geometry": {"coordinates":[-73.95,22.36667000000001],"type":"Point"}
}