{
  "type": "Feature",
  "properties": {
    "gn:admin1_code":"51.0",
    "gn:asciiname":"Pure Gold",
    "gn:country_code":"BS",
    "gn:dem":14,
    "gn:feature_class":"P",
    "gn:feature_code":"PPL",
    "gn:name":"Pure Gold",
    "gn:population":0,
    "gn:timezone":"America/Nassau",
    "iso:country":"BS",
    "wof:name":"Pure Gold",
    "wof:placetype":"locality"
},
  "geometry": {"coordinates":[-77.53333000000001,23.96667],"type":"Point"}
}