{
  "type": "Feature",
  "properties": {
    "iso:country":"BS",
    "name:unk_x_variant":[
        "Philippi Settlement"
    ],
    "qs:gn_country":"BS",
    "qs:gn_fcode":"PPL",
    "qs:gn_pop":0,
    "qs:name":"Pinders Point",
    "qs:name_adm0":"The Bahamas",
    "qs:name_adm1":"City of Freeport",
    "qs:photos":112,
    "qs:photos_1k":23,
    "qs:photos_9k":1,
    "qs:photos_9r":3,
    "qs:photos_all":112,
    "qs:photos_sr":3,
    "qs:placetype":"Town",
    "qs:pop_sr":"0",
    "qs:woe_adm0":23424758,
    "wof:name":"Pinders Point",
    "wof:placetype":"locality"
},
  "geometry": {"coordinates":[-78.68333,26.48333],"type":"Point"}
}