{
  "type": "Feature",
  "properties": {
    "iso:country":"BS",
    "name:deu_x_preferred":[
        "Sandy Point"
    ],
    "name:eng_x_preferred":[
        "Sandy Point"
    ],
    "name:jpn_x_preferred":[
        "\u30b5\u30f3\u30c7\u30a3\u30fc\u30fb\u30dd\u30a4\u30f3\u30c8"
    ],
    "name:nld_x_preferred":[
        "Sandy Point"
    ],
    "name:unk_x_variant":[
        "Sandy Point Settlement"
    ],
    "qs:gn_country":"BS",
    "qs:gn_fcode":"PPL",
    "qs:gn_pop":0,
    "qs:name":"Sandy Point",
    "qs:name_adm0":"The Bahamas",
    "qs:name_adm1":"South Abaco",
    "qs:photos":19,
    "qs:photos_1k":4,
    "qs:photos_9k":1,
    "qs:photos_9r":1,
    "qs:photos_all":19,
    "qs:photos_sr":1,
    "qs:placetype":"Town",
    "qs:pop_sr":"0",
    "qs:woe_adm0":23424758,
    "wd:wordcount":268,
    "wof:name":"Sandy Point",
    "wof:placetype":"locality"
},
  "geometry": {"coordinates":[-77.39,26.02052],"type":"Point"}
}