{
  "type": "Feature",
  "properties": {
    "gn:asciiname":"Eleuthera",
    "gn:country_code":"BS",
    "gn:dem":26,
    "gn:feature_class":"P",
    "gn:feature_code":"PPL",
    "gn:name":"Eleuthera",
    "gn:population":0,
    "gn:timezone":"America/Nassau",
    "iso:country":"BS",
    "wof:name":"Eleuthera",
    "wof:placetype":"locality"
},
  "geometry": {"coordinates":[-76.15023000000002,25.136],"type":"Point"}
}