{
  "type": "Feature",
  "properties": {
    "gn:admin1_code":"6.0",
    "gn:asciiname":"Orange Creek",
    "gn:country_code":"BS",
    "gn:dem":-5,
    "gn:feature_class":"P",
    "gn:feature_code":"PPL",
    "gn:name":"Orange Creek",
    "gn:population":0,
    "gn:timezone":"America/Nassau",
    "iso:country":"BS",
    "wof:name":"Orange Creek",
    "wof:placetype":"locality"
},
  "geometry": {"coordinates":[-75.71666999999999,24.65],"type":"Point"}
}