{
  "type": "Feature",
  "properties": {
    "gn:asciiname":"Rainbow Bay",
    "gn:country_code":"BS",
    "gn:dem":16,
    "gn:feature_class":"P",
    "gn:feature_code":"PPL",
    "gn:name":"Rainbow Bay",
    "gn:population":0,
    "gn:timezone":"America/Nassau",
    "iso:country":"BS",
    "name:ceb_x_preferred":[
        "Rainbow Bay"
    ],
    "wof:name":"Rainbow Bay",
    "wof:placetype":"locality"
},
  "geometry": {"coordinates":[-76.42764,25.3334],"type":"Point"}
}