{
  "type": "Feature",
  "properties": {
    "gn:country":"BS",
    "gn:fcode":"PPL",
    "gn:pop":8413,
    "iso:country":"BS",
    "name:ara_x_preferred":[
        "\u0643\u0648\u0628\u0631\u062a\u0627\u0648\u0646"
    ],
    "name:deu_x_preferred":[
        "Cooper\u2019s Town"
    ],
    "name:eng_x_preferred":[
        "Cooper\u2019s Town"
    ],
    "name:eng_x_variant":[
        "Coopers Town"
    ],
    "name:fas_x_preferred":[
        "\u06a9\u0648\u067e\u0631 \u062a\u0627\u0648\u0646"
    ],
    "name:fra_x_preferred":[
        "Coopers Town"
    ],
    "name:heb_x_preferred":[
        "\u05e7\u05d5\u05e4\u05e8\u05e1 \u05d8\u05d0\u05d5\u05df"
    ],
    "name:jpn_x_preferred":[
        "\u30af\u30fc\u30d1\u30fc\u30ba\u30fb\u30bf\u30a6\u30f3"
    ],
    "name:nld_x_preferred":[
        "Coopers Town"
    ],
    "name:pol_x_preferred":[
        "Coopers Town"
    ],
    "name:por_x_preferred":[
        "Coopers Town"
    ],
    "name:ron_x_preferred":[
        "Coopers Town"
    ],
    "name:rus_x_preferred":[
        "\u041a\u0443\u043f\u0435\u0440\u0441 \u0422\u0430\u0443\u043d"
    ],
    "name:spa_x_preferred":[
        "Coopers Town"
    ],
    "name:swe_x_preferred":[
        "Coopers Town"
    ],
    "qs:name":"Cooper\u2019s Town",
    "qs:photos_9r":0,
    "qs:photos_sr":0,
    "qs:pop_sr":"5",
    "wof:name":"Cooper\u2019s Town",
    "wof:placetype":"locality",
    "wof:population":8413
},
  "geometry": {"coordinates":[-77.51667,26.86667],"type":"Point"}
}