{
  "type": "Feature",
  "properties": {
    "gn:admin1_code":"53.0",
    "gn:asciiname":"Spanish Wells",
    "gn:country_code":"BS",
    "gn:dem":9,
    "gn:feature_class":"P",
    "gn:feature_code":"PPLA",
    "gn:name":"Spanish Wells",
    "gn:population":1500,
    "gn:timezone":"America/Nassau",
    "iso:country":"BS",
    "name:ceb_x_preferred":[
        "Spanish Wells District"
    ],
    "name:eng_x_preferred":[
        "Spanish Wells Settlement"
    ],
    "name:eng_x_variant":[
        "Spanish Wells"
    ],
    "name:fas_x_preferred":[
        "\u0627\u0633\u067e\u0646\u06cc\u0634 \u0648\u0644\u0632"
    ],
    "name:fin_x_preferred":[
        "Spanish Wells"
    ],
    "name:fra_x_preferred":[
        "Spanish Wells"
    ],
    "name:glg_x_preferred":[
        "Spanish Wells"
    ],
    "name:ind_x_preferred":[
        "Spanish Wells"
    ],
    "name:ita_x_preferred":[
        "Spanish Wells"
    ],
    "name:kor_x_preferred":[
        "\uc2a4\ud328\ub2c8\uc2dc\uc6f0\uc2a4"
    ],
    "name:nld_x_preferred":[
        "Spanish Wells"
    ],
    "name:pol_x_preferred":[
        "Spanish Wells"
    ],
    "name:por_x_preferred":[
        "Spanish Wells"
    ],
    "name:rus_x_preferred":[
        "\u0421\u043f\u044d\u043d\u0438\u0448-\u0423\u044d\u043b\u043b\u0441"
    ],
    "name:spa_x_preferred":[
        "Spanish Wells"
    ],
    "name:swe_x_preferred":[
        "Spanish Wells District"
    ],
    "name:urd_x_preferred":[
        "\u0633\u067e\u06cc\u0646\u0634 \u0648\u06cc\u0644\u0632"
    ],
    "wof:name":"Spanish Wells",
    "wof:placetype":"locality",
    "wof:population":1500
},
  "geometry": {"coordinates":[-76.76405,25.54717],"type":"Point"}
}