{
  "type": "Feature",
  "properties": {
    "gn:admin1_code":"53.0",
    "gn:asciiname":"Spanish Wells",
    "gn:country_code":"BS",
    "gn:dem":9,
    "gn:feature_class":"P",
    "gn:feature_code":"PPLA",
    "gn:name":"Spanish Wells",
    "gn:population":1500,
    "gn:timezone":"America/Nassau",
    "iso:country":"BS",
    "name:eng_x_preferred":[
        "Spanish Wells Settlement"
    ],
    "name:eng_x_variant":[
        "Spanish Wells"
    ],
    "wof:name":"Spanish Wells",
    "wof:placetype":"locality",
    "wof:population":1500
},
  "geometry": {"coordinates":[-76.76405,25.54717],"type":"Point"}
}