{
  "type": "Feature",
  "properties": {
    "gn:admin1_code":"15.0",
    "gn:asciiname":"Deadman's Cay",
    "gn:country_code":"BS",
    "gn:dem":4,
    "gn:feature_class":"P",
    "gn:feature_code":"PPL",
    "gn:name":"Deadman's Cay",
    "gn:population":0,
    "gn:timezone":"America/Nassau",
    "iso:country":"BS",
    "name:eng_x_preferred":[
        "Deadman's Cay Settlement"
    ],
    "name:eng_x_variant":[
        "Deadman's Cay"
    ],
    "wof:name":"Deadman's Cay",
    "wof:placetype":"locality"
},
  "geometry": {"coordinates":[-75.1131,23.17919],"type":"Point"}
}