{
  "type": "Feature",
  "properties": {
    "gn:admin1_code":"51.0",
    "gn:asciiname":"Kemps Bay",
    "gn:country_code":"BS",
    "gn:dem":6,
    "gn:feature_class":"P",
    "gn:feature_code":"PPL",
    "gn:name":"Kemps Bay",
    "gn:population":0,
    "gn:timezone":"America/Nassau",
    "iso:country":"BS",
    "name:und_x_variant":[
        "Kemps Bay Settlement",
        "Kemps Bay"
    ],
    "wof:name":"Kemps Bay",
    "wof:placetype":"locality"
},
  "geometry": {"coordinates":[-77.53343000000002,24.027],"type":"Point"}
}