{
  "type": "Feature",
  "properties": {
    "gn:admin1_code":"43.0",
    "gn:asciiname":"Man of War Cay Settlement",
    "gn:country_code":"BS",
    "gn:dem":1,
    "gn:feature_class":"P",
    "gn:feature_code":"PPL",
    "gn:name":"Man of War Cay Settlement",
    "gn:population":0,
    "gn:timezone":"America/Nassau",
    "iso:country":"BS",
    "name:eng_x_preferred":[
        "Man of War Cay Settlement"
    ],
    "name:eng_x_variant":[
        "Man of War Cay"
    ],
    "wof:name":"Man of War Cay Settlement",
    "wof:placetype":"locality"
},
  "geometry": {"coordinates":[-77.00076999999997,26.59536],"type":"Point"}
}