{
  "type": "Feature",
  "properties": {
    "gn:admin1_code":"48.0",
    "gn:asciiname":"Current Island Settlement",
    "gn:country_code":"BS",
    "gn:dem":-9999,
    "gn:feature_class":"P",
    "gn:feature_code":"PPL",
    "gn:name":"Current Island Settlement",
    "gn:population":0,
    "gn:timezone":"America/Nassau",
    "iso:country":"BS",
    "name:und_x_variant":[
        "Bar Bay Settlement",
        "Current Island Settlement"
    ],
    "wof:name":"Current Island Settlement",
    "wof:placetype":"locality"
},
  "geometry": {"coordinates":[-76.81622,25.34494],"type":"Point"}
}