{
  "type": "Feature",
  "properties": {
    "gn:admin1_code":"23.0",
    "gn:asciiname":"Belair Estates",
    "gn:country_code":"BS",
    "gn:dem":9,
    "gn:feature_class":"P",
    "gn:feature_code":"PPLL",
    "gn:name":"Belair Estates",
    "gn:population":0,
    "gn:timezone":"America/Nassau",
    "iso:country":"BS",
    "wof:name":"Belair Estates",
    "wof:placetype":"locality"
},
  "geometry": {"coordinates":[-77.36667,25.01667],"type":"Point"}
}