{
  "type": "Feature",
  "properties": {
    "gn:admin1_code":"49.0",
    "gn:asciiname":"Port Boyd",
    "gn:country_code":"BS",
    "gn:dem":16,
    "gn:feature_class":"P",
    "gn:feature_code":"PPL",
    "gn:name":"Port Boyd",
    "gn:population":0,
    "gn:timezone":"America/Nassau",
    "iso:country":"BS",
    "name:und_x_variant":[
        "Port Boyd Settlement",
        "Port Boyd"
    ],
    "wof:name":"Port Boyd",
    "wof:placetype":"locality"
},
  "geometry": {"coordinates":[-74.82068000000002,23.70354],"type":"Point"}
}