{
  "type": "Feature",
  "properties": {
    "gn:admin1_code":"54.0",
    "gn:asciiname":"Sea Grape",
    "gn:country_code":"BS",
    "gn:dem":-9999,
    "gn:feature_class":"P",
    "gn:feature_code":"PPL",
    "gn:name":"Sea Grape",
    "gn:population":0,
    "gn:timezone":"America/Nassau",
    "iso:country":"BS",
    "name:und_x_variant":[
        "Sea Grape Village",
        "Sea Grape"
    ],
    "wof:name":"Sea Grape",
    "wof:placetype":"locality"
},
  "geometry": {"coordinates":[-78.81667,26.53333],"type":"Point"}
}