{
  "type": "Feature",
  "properties": {
    "gn:admin1_code":"15.0",
    "gn:asciiname":"McKenzie",
    "gn:country_code":"BS",
    "gn:dem":6,
    "gn:feature_class":"P",
    "gn:feature_code":"PPL",
    "gn:name":"McKenzie",
    "gn:population":0,
    "gn:timezone":"America/Nassau",
    "iso:country":"BS",
    "wof:name":"McKenzie",
    "wof:placetype":"locality"
},
  "geometry": {"coordinates":[-75.06667,23.13333],"type":"Point"}
}