{
  "type": "Feature",
  "properties": {
    "gn:admin1_code":"23.0",
    "gn:asciiname":"Waterloo",
    "gn:cc2":"BS",
    "gn:country_code":"BS",
    "gn:dem":12,
    "gn:feature_class":"P",
    "gn:feature_code":"PPL",
    "gn:name":"Waterloo",
    "gn:population":0,
    "gn:timezone":"America/Nassau",
    "iso:country":"BS",
    "name:und_x_variant":[
        "West Waterloo",
        "Waterloo"
    ],
    "wof:name":"Waterloo",
    "wof:placetype":"locality"
},
  "geometry": {"coordinates":[-77.53333000000001,25.03333],"type":"Point"}
}