{
  "type": "Feature",
  "properties": {
    "gn:admin1_code":"40.0",
    "gn:asciiname":"Fairfield",
    "gn:country_code":"BS",
    "gn:dem":4,
    "gn:feature_class":"P",
    "gn:feature_code":"PPL",
    "gn:name":"Fairfield",
    "gn:population":0,
    "gn:timezone":"America/Nassau",
    "iso:country":"BS",
    "wof:name":"Fairfield",
    "wof:placetype":"locality"
},
  "geometry": {"coordinates":[-74.21666999999999,22.78333],"type":"Point"}
}