{
  "type": "Feature",
  "properties": {
    "gn:asciiname":"North Cat Cay",
    "gn:country_code":"BS",
    "gn:dem":-9999,
    "gn:feature_class":"P",
    "gn:feature_code":"PPL",
    "gn:name":"North Cat Cay",
    "gn:population":0,
    "gn:timezone":"America/Nassau",
    "iso:country":"BS",
    "wof:name":"North Cat Cay",
    "wof:placetype":"locality"
},
  "geometry": {"coordinates":[-79.28434,25.55549],"type":"Point"}
}